regex_e_match/__init__.py
regex_e_match_MW-0.0.1.dist-info/METADATA
regex_e_match_MW-0.0.1.dist-info/WHEEL
regex_e_match_MW-0.0.1.dist-info/top_level.txt
regex_e_match_MW-0.0.1.dist-info/RECORD
