Metadata-Version: 2.1
Name: regex-e-match-MW
Version: 0.0.1
Summary: Makes matching of regex statements easy.
Home-page: UNKNOWN
Author: MW
Author-email: 
License: UNKNOWN
Platform: UNKNOWN
Classifier: Programming Language :: Python :: 3
Classifier: License :: OSI Approved :: MIT License
Classifier: Operating System :: OS Independent
Requires-Python: >=3.6
